Metadata-Version: 2.1
Name: dmstudiopy
Version: 0.0.7
Summary: Python package for Datamine Studio scripting.
Home-page: https://github.com/seanhoran/dmstudio
Author: Sean Horan, Renan Lopes
Author-email: renanglopes@gmail.com
License: UNKNOWN
Project-URL: Bug Reports, https://github.com/seanhoran/dmstudio/issues
Platform: UNKNOWN
Classifier: Development Status :: 4 - Beta
Classifier: Intended Audience :: Science/Research
Classifier: Programming Language :: Python :: 3
Classifier: License :: OSI Approved :: MIT License
Classifier: Operating System :: OS Independent
Classifier: Topic :: Scientific/Engineering :: GIS
Classifier: Topic :: Scientific/Engineering :: Mathematics
Classifier: Topic :: Scientific/Engineering :: Information Analysis
Classifier: Topic :: Software Development :: Libraries
Requires-Python: >=3.6
